psytracer/__init__.py
psytracer-0.0.1.dist-info/METADATA
psytracer-0.0.1.dist-info/WHEEL
psytracer-0.0.1.dist-info/top_level.txt
psytracer-0.0.1.dist-info/RECORD
